cycl/__init__.py
cycl/__main__.py
cycl/cli.py
cycl/cycl.py
cycl/py.typed
cycl/models/__init__.py
cycl/models/node_data.py
cycl/utils/__init__.py
cycl/utils/cdk.py
cycl/utils/cfn.py
cycl/utils/log_config.py
cycl/utils/testing.py
cycl-1.2.11.dist-info/licenses/LICENSE
cycl-1.2.11.dist-info/METADATA
cycl-1.2.11.dist-info/WHEEL
cycl-1.2.11.dist-info/entry_points.txt
cycl-1.2.11.dist-info/top_level.txt
cycl-1.2.11.dist-info/RECORD
