Metadata-Version: 2.4
Name: cycl
Version: 1.2.11
Summary: cycl is a CLI and Python SDK to help identify cross-stack import/export circular dependencies, for a given AWS account and region.
License: MIT
Project-URL: Repository, http://github.com/tcm5343/cycl
Project-URL: Documentation, https://tcm5343.github.io/cycl/index.html
Keywords: aws,cdk,cycle,circular,dependency,infrastructure,boto3,cloud
Classifier: Intended Audience :: Developers
Classifier: Natural Language :: English
Classifier: Programming Language :: Python :: 3.10
Classifier: Programming Language :: Python :: 3.11
Classifier: Programming Language :: Python :: 3.12
Classifier: Programming Language :: Python :: 3.13
Classifier: Programming Language :: Python :: 3.14
Classifier: Programming Language :: Python :: 3.9
Classifier: Programming Language :: Python :: 3
Classifier: Programming Language :: Python
Classifier: Topic :: Software Development
Requires-Python: >=3.9
License-File: LICENSE
Requires-Dist: boto3>=1.26
Requires-Dist: networkx~=3.0
Provides-Extra: test
Requires-Dist: pytest-cov==7.0.0; extra == "test"
Requires-Dist: pytest-sugar==1.1.1; extra == "test"
Requires-Dist: pytest-subtests==0.15.0; extra == "test"
Requires-Dist: pytest==7.4.4; extra == "test"
Requires-Dist: pytest-xdist==3.8.0; extra == "test"
Provides-Extra: validation
Requires-Dist: boto3-stubs[essential]==1.40.32; extra == "validation"
Requires-Dist: mypy==1.18.2; extra == "validation"
Requires-Dist: ruff==0.14.1; extra == "validation"
Requires-Dist: types-networkx==3.4.2.20250509; extra == "validation"
Provides-Extra: doc
Requires-Dist: myst-parser==3.0.1; extra == "doc"
Requires-Dist: sphinx_rtd_theme==3.0.2; extra == "doc"
Requires-Dist: sphinx-argparse==0.4.0; extra == "doc"
Requires-Dist: sphinx-autobuild==2024.10.3; extra == "doc"
Requires-Dist: sphinx==7.4.7; extra == "doc"
Provides-Extra: dist
Requires-Dist: build==1.3.0; extra == "dist"
Requires-Dist: twine==6.1.0; extra == "dist"
Provides-Extra: e2e
Requires-Dist: pytest==7.4.4; extra == "e2e"
Requires-Dist: aws-cdk-lib==2.172.0; extra == "e2e"
Requires-Dist: constructs<11.0.0,>=10.0.0; extra == "e2e"
Dynamic: license-file
